app.py
common/arguments.py
common/base.py
common/config.py
common/console.py
common/doctor.py
common/errors.py
common/format_markdown.py
common/http_response.py
common/json.py
common/json_parser.py
common/loading.py
common/prompts.py
common/reflection.py
common/result.py
common/updater.py
common/command/base_command.py
common/command/base_command_handler.py
common/command/execute_command_handler.py
domains/commit/command/commit.py
domains/setup/__init__.py
domains/setup/command/__init__.py
domains/setup/command/setup.py
quick_assistant-0.2.9.dist-info/METADATA
quick_assistant-0.2.9.dist-info/WHEEL
quick_assistant-0.2.9.dist-info/entry_points.txt
quick_assistant-0.2.9.dist-info/RECORD
