Metadata-Version: 2.4
Name: quick-assistant
Version: 0.2.9
Summary: Global CLI tool for productivity
Project-URL: Homepage, https://github.com/rafaeelricco/quick-assistant
Project-URL: Repository, https://github.com/rafaeelricco/quick-assistant
Author-email: Rafael Ricco <rafaelricco10@gmail.com>
License-Expression: MIT
Requires-Python: >=3.11
Requires-Dist: charset-normalizer>=3.0.0
Requires-Dist: google-genai>=1.26.0
Requires-Dist: packaging>=24.0
Requires-Dist: pydantic>=2.11.7
Requires-Dist: python-dotenv>=1.1.1
Requires-Dist: questionary>=2.0.0
Requires-Dist: requests>=2.31.0
Requires-Dist: rich>=14.0.0
